pyavm/__init__.py
pyavm/_version.py
pyavm/avm.py
pyavm/cv.py
pyavm/datatypes.py
pyavm/embed.py
pyavm/exceptions.py
pyavm/extract.py
pyavm/jpeg.py
pyavm/png.py
pyavm/specs.py
pyavm/wcs_utils.py
pyavm/tests/__init__.py
pyavm/tests/test_avm.py
pyavm/tests/test_header.py
pyavm/tests/test_io.py
pyavm/tests/test_main.py
pyavm/tests/test_specs.py
pyavm/tests/test_wcs_utils.py
pyavm/tests/data/3c321.avm.xml
pyavm/tests/data/a3627_wcs_metadata.xml
pyavm/tests/data/eso_eso1723a_320.jpg
pyavm/tests/data/eso_eso1723a_320.png
pyavm/tests/data/example_header.hdr
pyavm/tests/data/heic0409a.xml
pyavm/tests/data/heic0515a.xml
pyavm/tests/data/kes75.xml
pyavm/tests/data/n132d.xml
pyavm/tests/data/opo0613a.xml
pyavm/tests/data/sig05-002a.xml
pyavm/tests/data/sig05-003a.xml
pyavm/tests/data/sig05-004a.xml
pyavm/tests/data/sig05-011.xml
pyavm/tests/data/sig05-013.xml
pyavm/tests/data/sig05-014.xml
pyavm/tests/data/sig05-015.xml
pyavm/tests/data/sig05-016.xml
pyavm/tests/data/sig05-017.xml
pyavm/tests/data/sig05-019b.xml
pyavm/tests/data/sig05-019d.xml
pyavm/tests/data/sig05-021-alpha.xml
pyavm/tests/data/sig05-021.xml
pyavm/tests/data/sig05-028a.xml
pyavm/tests/data/sig05-028b.xml
pyavm/tests/data/sig05-028c.xml
pyavm/tests/data/sig06-003.xml
pyavm/tests/data/sig06-010.xml
pyavm/tests/data/sig06-012b.xml
pyavm/tests/data/sig06-012c.xml
pyavm/tests/data/sig06-013.xml
pyavm/tests/data/sig06-021a.xml
pyavm/tests/data/sig06-027.xml
pyavm/tests/data/sig07-006.xml
pyavm/tests/data/sig07-009.xml
pyavm/tests/data/sig07-016.xml
pyavm/tests/data/snr0509_xray.xml
pyavm/tests/data/ssc2003-06b1.xml
pyavm/tests/data/ssc2003-06b2.xml
pyavm/tests/data/ssc2003-06c1.xml
pyavm/tests/data/ssc2003-06d1.xml
pyavm/tests/data/ssc2003-06d3.xml
pyavm/tests/data/ssc2003-06d4.xml
pyavm/tests/data/ssc2003-06d5.xml
pyavm/tests/data/ssc2004-04a1.xml
pyavm/tests/data/ssc2004-04a3.xml
pyavm/tests/data/ssc2004-04a4.xml
pyavm/tests/data/ssc2004-06a1-alpha.xml
pyavm/tests/data/ssc2004-06a1.xml
pyavm-0.9.8.dist-info/licenses/LICENSE
pyavm-0.9.8.dist-info/METADATA
pyavm-0.9.8.dist-info/WHEEL
pyavm-0.9.8.dist-info/top_level.txt
pyavm-0.9.8.dist-info/RECORD
