Metadata-Version: 2.4
Name: PyAVM
Version: 0.9.8
Summary: Simple pure-python AVM meta-data handling
Author-email: Thomas Robitaille <thomas.robitaille@gmail.com>
License: MIT
Project-URL: documentation, http://astrofrog.github.io/pyavm/
Project-URL: homepage, http://astrofrog.github.io/pyavm/
Project-URL: repository, https://github.com/astrofrog/pyavm
Keywords: Scientific/Engineering
Classifier: Development Status :: 4 - Beta
Classifier: License :: OSI Approved :: MIT License
Classifier: Programming Language :: Python
Classifier: Programming Language :: Python :: 3 :: Only
Classifier: Programming Language :: Python :: 3.8
Classifier: Programming Language :: Python :: 3.9
Classifier: Programming Language :: Python :: 3.10
Classifier: Programming Language :: Python :: 3.11
Classifier: Programming Language :: Python :: 3.12
Requires-Python: >=3.8
License-File: LICENSE
Provides-Extra: test
Requires-Dist: pytest; extra == "test"
Requires-Dist: pytest-cov; extra == "test"
Provides-Extra: testall
Requires-Dist: astropy; extra == "testall"
Requires-Dist: numpy; extra == "testall"
Requires-Dist: pillow; extra == "testall"
Dynamic: license-file
